{"title":null,"periodInfo":"4 الأحد","bible":{"id":11,"name":"الكتاب المقدس باللغة العربية، فان دايك","languageId":3,"versificationSchemeId":null},"bibles":[{"id":3,"name":"Arabic","languageId":3,"versificationSchemeId":null},{"id":11,"name":"الكتاب المقدس باللغة العربية، فان دايك","languageId":3,"versificationSchemeId":null}],"sections":[{"id":1,"title":"العشية","subSections":[{"id":1,"title":"المزمور والإنجيل","introduction":"قفوا بخوف أمام الله، وانصتوا لسماع الإنجيل المقدس. فصل شريف من بشارة معلمنا متى الإنجيلي. بركته تكون مع جميعنا، آمين.","readings":[{"id":1,"title":null,"introduction":"من مزامير أبينا داود النبي والملك ، بركاته يكون معنا أمين","conclusion":"هللويا!","passages":[{"bookId":19,"bookTranslation":"مزامير","chapter":84,"ref":"84:8,4","verses":[{"id":783810,"bibleId":11,"bookId":19,"chapter":84,"number":8,"text":"يَارَبُّ إِلَهَ ٱلْجُنُودِ، ٱسْمَعْ صَلَاتِي، وَٱصْغَ يَا إِلَهَ يَعْقُوبَ. سِلَاهْ."},{"id":783806,"bibleId":11,"bookId":19,"chapter":84,"number":4,"text":"طُوبَى لِلسَّاكِنِينَ فِي بَيْتِكَ، أَبَدًا يُسَبِّحُونَكَ. سِلَاهْ."}]}],"html":null},{"id":2,"title":null,"introduction":"مبارك الآتي باسم الرب إله القوات ، ربنا وإلهنا ومخلصنا وملكنا كلنا، يسوع المسيح ابن الله الحي، الذي له المجد للأبد آمين.","conclusion":"ولله المجد لله الى الابد آمين.","passages":[{"bookId":40,"bookTranslation":"متى","chapter":5,"ref":"5:34-48","verses":[{"id":791811,"bibleId":11,"bookId":40,"chapter":5,"number":34,"text":"وَأَمَّا أَنَا فَأَقُولُ لَكُمْ: لَا تَحْلِفُوا ٱلْبَتَّةَ، لَا بِٱلسَّمَاءِ لِأَنَّهَا كُرْسِيُّ ٱللهِ،"},{"id":791812,"bibleId":11,"bookId":40,"chapter":5,"number":35,"text":"وَلَا بِٱلْأَرْضِ لِأَنَّهَا مَوْطِئُ قَدَمَيْهِ، وَلَا بِأُورُشَلِيمَ لِأَنَّهَا مَدِينَةُ ٱلْمَلِكِ ٱلْعَظِيمِ."},{"id":791813,"bibleId":11,"bookId":40,"chapter":5,"number":36,"text":"وَلَا تَحْلِفْ بِرَأْسِكَ، لِأَنَّكَ لَا تَقْدِرُ أَنْ تَجْعَلَ شَعْرَةً وَاحِدَةً بَيْضَاءَ أَوْ سَوْدَاءَ."},{"id":791814,"bibleId":11,"bookId":40,"chapter":5,"number":37,"text":"بَلْ لِيَكُنْ كَلَامُكُمْ: نَعَمْ نَعَمْ، لَا لَا. وَمَا زَادَ عَلَى ذَلِكَ فَهُوَ مِنَ ٱلشِّرِّيرِ."},{"id":791815,"bibleId":11,"bookId":40,"chapter":5,"number":38,"text":"«سَمِعْتُمْ أَنَّهُ قِيلَ: عَيْنٌ بِعَيْنٍ وَسِنٌّ بِسِنٍّ."},{"id":791816,"bibleId":11,"bookId":40,"chapter":5,"number":39,"text":"وَأَمَّا أَنَا فَأَقُولُ لَكُمْ: لَا تُقَاوِمُوا ٱلشَّرَّ، بَلْ مَنْ لَطَمَكَ عَلَى خَدِّكَ ٱلْأَيْمَنِ فَحَوِّلْ لَهُ ٱلْآخَرَ أَيْضًا."},{"id":791817,"bibleId":11,"bookId":40,"chapter":5,"number":40,"text":"وَمَنْ أَرَادَ أَنْ يُخَاصِمَكَ وَيَأْخُذَ ثَوْبَكَ فَٱتْرُكْ لَهُ ٱلرِّدَاءَ أَيْضًا."},{"id":791818,"bibleId":11,"bookId":40,"chapter":5,"number":41,"text":"وَمَنْ سَخَّرَكَ مِيلًا وَاحِدًا فَٱذْهَبْ مَعَهُ ٱثْنَيْنِ."},{"id":791819,"bibleId":11,"bookId":40,"chapter":5,"number":42,"text":"مَنْ سَأَلَكَ فَأَعْطِهِ، وَمَنْ أَرَادَ أَنْ يَقْتَرِضَ مِنْكَ فَلَا تَرُدَّهُ."},{"id":791820,"bibleId":11,"bookId":40,"chapter":5,"number":43,"text":"«سَمِعْتُمْ أَنَّهُ قِيلَ: تُحِبُّ قَرِيبَكَ وَتُبْغِضُ عَدُوَّكَ."},{"id":791821,"bibleId":11,"bookId":40,"chapter":5,"number":44,"text":"وَأَمَّا أَنَا فَأَقُولُ لَكُمْ: أَحِبُّوا أَعْدَاءَكُمْ. بَارِكُوا لَاعِنِيكُمْ. أَحْسِنُوا إِلَى مُبْغِضِيكُمْ، وَصَلُّوا لِأَجْلِ ٱلَّذِينَ يُسِيئُونَ إِلَيْكُمْ وَيَطْرُدُونَكُمْ،"},{"id":791822,"bibleId":11,"bookId":40,"chapter":5,"number":45,"text":"لِكَيْ تَكُونُوا أَبْنَاءَ أَبِيكُمُ ٱلَّذِي فِي ٱلسَّمَاوَاتِ، فَإِنَّهُ يُشْرِقُ شَمْسَهُ عَلَى ٱلْأَشْرَارِ وَٱلصَّالِحِينَ، وَيُمْطِرُ عَلَى ٱلْأَبْرَارِ وَٱلظَّالِمِينَ."},{"id":791823,"bibleId":11,"bookId":40,"chapter":5,"number":46,"text":"لِأَنَّهُ إِنْ أَحْبَبْتُمُ ٱلَّذِينَ يُحِبُّونَكُمْ، فَأَيُّ أَجْرٍ لَكُمْ؟ أَلَيْسَ ٱلْعَشَّارُونَ أَيْضًا يَفْعَلُونَ ذَلِكَ؟"},{"id":791824,"bibleId":11,"bookId":40,"chapter":5,"number":47,"text":"وَإِنْ سَلَّمْتُمْ عَلَى إِخْوَتِكُمْ فَقَطْ، فَأَيَّ فَضْلٍ تَصْنَعُونَ؟ أَلَيْسَ ٱلْعَشَّارُونَ أَيْضًا يَفْعَلُونَ هَكَذَا؟"},{"id":791825,"bibleId":11,"bookId":40,"chapter":5,"number":48,"text":"فَكُونُوا أَنْتُمْ كَامِلِينَ كَمَا أَنَّ أَبَاكُمُ ٱلَّذِي فِي ٱلسَّمَاوَاتِ هُوَ كَامِلٌ."}]}],"html":null}]}]},{"id":2,"title":"باكر","subSections":[{"id":1,"title":"المزمور والإنجيل","introduction":"قفوا بخوف أمام الله، وانصتوا لسماع الإنجيل المقدس. فصل شريف من بشارة معلمنا يوحنا الإنجيلي. بركته تكون مع جميعنا، آمين.","readings":[{"id":1,"title":null,"introduction":"من مزامير أبينا داود النبي والملك ، بركاته يكون معنا أمين","conclusion":"هللويا!","passages":[{"bookId":19,"bookTranslation":"مزامير","chapter":61,"ref":"61:5-8","verses":[{"id":783367,"bibleId":11,"bookId":19,"chapter":61,"number":5,"text":"لِأَنَّكَ أَنْتَ يَا ٱللهُ ٱسْتَمَعْتَ نُذُورِي. أَعْطَيْتَ مِيرَاثَ خَائِفِي ٱسْمِكَ."},{"id":783368,"bibleId":11,"bookId":19,"chapter":61,"number":6,"text":"إِلَى أَيَّامِ ٱلْمَلِكِ تُضِيفُ أَيَّامًا. سِنِينُهُ كَدَوْرٍ فَدَوْرٍ."},{"id":783369,"bibleId":11,"bookId":19,"chapter":61,"number":7,"text":"يَجْلِسُ قُدَّامَ ٱللهِ إِلَى ٱلدَّهْرِ. ٱجْعَلْ رَحْمَةً وَحَقًّا يَحْفَظَانِهِ."},{"id":783370,"bibleId":11,"bookId":19,"chapter":61,"number":8,"text":"هَكَذَا أُرَنِّمُ لِٱسْمِكَ إِلَى ٱلْأَبَدِ، لِوَفَاءِ نُذُورِي يَوْمًا فَيَوْمًا."}]}],"html":null},{"id":2,"title":null,"introduction":"مبارك الآتي باسم الرب إله القوات ، ربنا وإلهنا ومخلصنا وملكنا كلنا، يسوع المسيح ابن الله الحي، الذي له المجد للأبد آمين.","conclusion":"ولله المجد لله الى الابد آمين.","passages":[{"bookId":43,"bookTranslation":"يوحنا","chapter":20,"ref":"20:1-18","verses":[{"id":795411,"bibleId":11,"bookId":43,"chapter":20,"number":1,"text":"وَفِي أَوَّلِ ٱلْأُسْبُوعِ جَاءَتْ مَرْيَمُ ٱلْمَجْدَلِيَّةُ إِلَى ٱلْقَبْرِ بَاكِرًا، وَٱلظَّلَامُ بَاقٍ. فَنَظَرَتِ ٱلْحَجَرَ مَرْفُوعًا عَنِ ٱلْقَبْرِ."},{"id":795412,"bibleId":11,"bookId":43,"chapter":20,"number":2,"text":"فَرَكَضَتْ وَجَاءَتْ إِلَى سِمْعَانَ بُطْرُسَ وَإِلَى ٱلتِّلْمِيذِ ٱلْآخَرِ ٱلَّذِي كَانَ يَسُوعُ يُحِبُّهُ، وَقَالَتْ لَهُمَا: «أَخَذُوا ٱلسَّيِّدَ مِنَ ٱلْقَبْرِ، وَلَسْنَا نَعْلَمُ أَيْنَ وَضَعُوهُ!»."},{"id":795413,"bibleId":11,"bookId":43,"chapter":20,"number":3,"text":"فَخَرَجَ بُطْرُسُ وَٱلتِّلْمِيذُ ٱلْآخَرُ وَأَتَيَا إِلَى ٱلْقَبْرِ."},{"id":795414,"bibleId":11,"bookId":43,"chapter":20,"number":4,"text":"وَكَانَ ٱلِٱثْنَانِ يَرْكُضَانِ مَعًا. فَسَبَقَ ٱلتِّلْمِيذُ ٱلْآخَرُ بُطْرُسَ وَجَاءَ أَوَّلًا إِلَى ٱلْقَبْرِ،"},{"id":795415,"bibleId":11,"bookId":43,"chapter":20,"number":5,"text":"وَٱنْحَنَى فَنَظَرَ ٱلْأَكْفَانَ مَوْضُوعَةً، وَلَكِنَّهُ لَمْ يَدْخُلْ."},{"id":795416,"bibleId":11,"bookId":43,"chapter":20,"number":6,"text":"ثُمَّ جَاءَ سِمْعَانُ بُطْرُسُ يَتْبَعُهُ، وَدَخَلَ ٱلْقَبْرَ وَنَظَرَ ٱلْأَكْفَانَ مَوْضُوعَةً،"},{"id":795417,"bibleId":11,"bookId":43,"chapter":20,"number":7,"text":"وَٱلْمِنْدِيلَ ٱلَّذِي كَانَ عَلَى رَأْسِهِ لَيْسَ مَوْضُوعًا مَعَ ٱلْأَكْفَانِ، بَلْ مَلْفُوفًا فِي مَوْضِعٍ وَحْدَهُ."},{"id":795418,"bibleId":11,"bookId":43,"chapter":20,"number":8,"text":"فَحِينَئِذٍ دَخَلَ أَيْضًا ٱلتِّلْمِيذُ ٱلْآخَرُ ٱلَّذِي جَاءَ أَوَّلًا إِلَى ٱلْقَبْرِ، وَرَأَى فَآمَنَ،"},{"id":795419,"bibleId":11,"bookId":43,"chapter":20,"number":9,"text":"لِأَنَّهُمْ لَمْ يَكُونُوا بَعْدُ يَعْرِفُونَ ٱلْكِتَابَ: أَنَّهُ يَنْبَغِي أَنْ يَقُومَ مِنَ ٱلْأَمْوَاتِ."},{"id":795420,"bibleId":11,"bookId":43,"chapter":20,"number":10,"text":"فَمَضَى ٱلتِّلْمِيذَانِ أَيْضًا إِلَى مَوْضِعِهِمَا."},{"id":795421,"bibleId":11,"bookId":43,"chapter":20,"number":11,"text":"أَمَّا مَرْيَمُ فَكَانَتْ وَاقِفَةً عِنْدَ ٱلْقَبْرِ خَارِجًا تَبْكِي. وَفِيمَا هِيَ تَبْكِي ٱنْحَنَتْ إِلَى ٱلْقَبْرِ،"},{"id":795422,"bibleId":11,"bookId":43,"chapter":20,"number":12,"text":"فَنَظَرَتْ مَلَاكَيْنِ بِثِيَابٍ بِيضٍ جَالِسَيْنِ وَاحِدًا عِنْدَ ٱلرَّأْسِ وَٱلْآخَرَ عِنْدَ ٱلرِّجْلَيْنِ، حَيْثُ كَانَ جَسَدُ يَسُوعَ مَوْضُوعًا."},{"id":795423,"bibleId":11,"bookId":43,"chapter":20,"number":13,"text":"فَقَالَا لَهَا: «يَا ٱمْرَأَةُ، لِمَاذَا تَبْكِينَ؟». قَالَتْ لَهُمَا: «إِنَّهُمْ أَخَذُوا سَيِّدِي، وَلَسْتُ أَعْلَمُ أَيْنَ وَضَعُوهُ!»."},{"id":795424,"bibleId":11,"bookId":43,"chapter":20,"number":14,"text":"وَلَمَّا قَالَتْ هَذَا ٱلْتَفَتَتْ إِلَى ٱلْوَرَاءِ، فَنَظَرَتْ يَسُوعَ وَاقِفًا، وَلَمْ تَعْلَمْ أَنَّهُ يَسُوعُ."},{"id":795425,"bibleId":11,"bookId":43,"chapter":20,"number":15,"text":"قَالَ لَهَا يَسُوعُ: «يَا ٱمْرَأَةُ، لِمَاذَا تَبْكِينَ؟ مَنْ تَطْلُبِينَ؟». فَظَنَّتْ تِلْكَ أَنَّهُ ٱلْبُسْتَانِيُّ، فَقَالَتْ لَهُ: «يَا سَيِّدُ، إِنْ كُنْتَ أَنْتَ قَدْ حَمَلْتَهُ فَقُلْ لِي أَيْنَ وَضَعْتَهُ، وَأَنَا آخُذُهُ»."},{"id":795426,"bibleId":11,"bookId":43,"chapter":20,"number":16,"text":"قَالَ لَهَا يَسُوعُ: «يَا مَرْيَمُ». فَٱلْتَفَتَتْ تِلْكَ وَقَالَتْ لَهُ: «رَبُّونِي!» ٱلَّذِي تَفْسِيرُهُ: يَا مُعَلِّمُ."},{"id":795427,"bibleId":11,"bookId":43,"chapter":20,"number":17,"text":"قَالَ لَهَا يَسُوعُ: «لَا تَلْمِسِينِي لِأَنِّي لَمْ أَصْعَدْ بَعْدُ إِلَى أَبِي. وَلَكِنِ ٱذْهَبِي إِلَى إِخْوَتِي وَقُولِي لَهُمْ: إِنِّي أَصْعَدُ إِلَى أَبِي وَأَبِيكُمْ وَإِلَهِي وَإِلَهِكُمْ»."},{"id":795428,"bibleId":11,"bookId":43,"chapter":20,"number":18,"text":"فَجَاءَتْ مَرْيَمُ ٱلْمَجْدَلِيَّةُ وَأَخْبَرَتِ ٱلتَّلَامِيذَ أَنَّهَا رَأَتِ ٱلرَّبَّ، وَأَنَّهُ قَالَ لَهَا هَذَا."}]}],"html":null}]}]},{"id":3,"title":"قداس","subSections":[{"id":3,"title":"البولس","introduction":null,"readings":[{"id":3,"title":null,"introduction":"فصل من رسالة معلمنا بولس الرسول  إلى   كولوسي بركاته تكون معنا آمين.","conclusion":"نعمة الله الآب تكون مع جميعكم. آمين.","passages":[{"bookId":51,"bookTranslation":"كولوسي","chapter":4,"ref":"4:2-18","verses":[{"id":798087,"bibleId":11,"bookId":51,"chapter":4,"number":2,"text":"وَاظِبُوا عَلَى ٱلصَّلَاةِ سَاهِرِينَ فِيهَا بِٱلشُّكْرِ،"},{"id":798088,"bibleId":11,"bookId":51,"chapter":4,"number":3,"text":"مُصَلِّينَ فِي ذَلِكَ لِأَجْلِنَا نَحْنُ أَيْضًا، لِيَفْتَحَ ٱلرَّبُّ لَنَا بَابًا لِلْكَلَامِ، لِنَتَكَلَّمَ بِسِرِّ ٱلْمَسِيحِ، ٱلَّذِي مِنْ أَجْلِهِ أَنَا مُوثَقٌ أَيْضًا،"},{"id":798089,"bibleId":11,"bookId":51,"chapter":4,"number":4,"text":"كَيْ أُظْهِرَهُ كَمَا يَجِبُ أَنْ أَتَكَلَّمَ."},{"id":798090,"bibleId":11,"bookId":51,"chapter":4,"number":5,"text":"اُسْلُكُوا بِحِكْمَةٍ مِنْ جِهَةِ ٱلَّذِينَ هُمْ مِنْ خَارِجٍ، مُفْتَدِينَ ٱلْوَقْتَ."},{"id":798091,"bibleId":11,"bookId":51,"chapter":4,"number":6,"text":"لِيَكُنْ كَلَامُكُمْ كُلَّ حِينٍ بِنِعْمَةٍ، مُصْلَحًا بِمِلْحٍ، لِتَعْلَمُوا كَيْفَ يَجِبُ أَنْ تُجَاوِبُوا كُلَّ وَاحِدٍ."},{"id":798092,"bibleId":11,"bookId":51,"chapter":4,"number":7,"text":"جَمِيعُ أَحْوَالِي سَيُعَرِّفُكُمْ بِهَا تِيخِيكُسُ ٱلْأَخُ ٱلْحَبِيبُ، وَٱلْخَادِمُ ٱلْأَمِينُ، وَٱلْعَبْدُ مَعَنَا فِي ٱلرَّبِّ،"},{"id":798093,"bibleId":11,"bookId":51,"chapter":4,"number":8,"text":"ٱلَّذِي أَرْسَلْتُهُ إِلَيْكُمْ لِهَذَا عَيْنِهِ، لِيَعْرِفَ أَحْوَالَكُمْ وَيُعَزِّيَ قُلُوبَكُمْ،"},{"id":798094,"bibleId":11,"bookId":51,"chapter":4,"number":9,"text":"مَعْ أُنِسِيمُسَ ٱلْأَخِ ٱلْأَمِينِ ٱلْحَبِيبِ ٱلَّذِي هُوَ مِنْكُمْ. هُمَا سَيُعَرِّفَانِكُمْ بِكُلِّ مَا هَهُنَا."},{"id":798095,"bibleId":11,"bookId":51,"chapter":4,"number":10,"text":"يُسَلِّمُ عَلَيْكُمْ أَرِسْتَرْخُسُ ٱلْمَأْسُورُ مَعِي، وَمَرْقُسُ ٱبْنُ أُخْتِ بَرْنَابَا، ٱلَّذِي أَخَذْتُمْ لِأَجْلِهِ وَصَايَا. إِنْ أَتَى إِلَيْكُمْ فَٱقْبَلُوهُ."},{"id":798096,"bibleId":11,"bookId":51,"chapter":4,"number":11,"text":"وَيَسُوعُ ٱلْمَدْعُوُّ يُسْطُسَ، ٱلَّذِينَ هُمْ مِنَ ٱلْخِتَانِ. هَؤُلَاءِ هُمْ وَحْدَهُمُ ٱلْعَامِلُونَ مَعِي لِمَلَكُوتِ ٱللهِ، ٱلَّذِينَ صَارُوا لِي تَسْلِيَةً."},{"id":798097,"bibleId":11,"bookId":51,"chapter":4,"number":12,"text":"يُسَلِّمُ عَلَيْكُمْ أَبَفْرَاسُ، ٱلَّذِي هُوَ مِنْكُمْ، عَبْدٌ لِلْمَسِيحِ، مُجَاهِدٌ كُلَّ حِينٍ لِأَجْلِكُمْ بِٱلصَّلَوَاتِ، لِكَيْ تَثْبُتُوا كَامِلِينَ وَمُمْتَلِئِينَ فِي كُلِّ مَشِيئَةِ ٱللهِ."},{"id":798098,"bibleId":11,"bookId":51,"chapter":4,"number":13,"text":"فَإِنِّي أَشْهَدُ فِيهِ أَنَّ لَهُ غَيْرَةً كَثِيرَةً لِأَجْلِكُمْ، وَلِأَجْلِ ٱلَّذِينَ فِي لَاوُدِكِيَّةَ، وَٱلَّذِينَ فِي هِيَرَابُولِيسَ."},{"id":798099,"bibleId":11,"bookId":51,"chapter":4,"number":14,"text":"يُسَلِّمُ عَلَيْكُمْ لُوقَا ٱلطَّبِيبُ ٱلْحَبِيبُ، وَدِيمَاسُ."},{"id":798100,"bibleId":11,"bookId":51,"chapter":4,"number":15,"text":"سَلِّمُوا عَلَى ٱلْإِخْوَةِ ٱلَّذِينَ فِي لَاوُدِكِيَّةَ، وَعَلَى نِمْفَاسَ وَعَلَى ٱلْكَنِيسَةِ ٱلَّتِي فِي بَيْتِهِ."},{"id":798101,"bibleId":11,"bookId":51,"chapter":4,"number":16,"text":"وَمَتَى قُرِئَتْ عِنْدَكُمْ هَذِهِ ٱلرِّسَالَةُ فَٱجْعَلُوهَا تُقْرَأُ أَيْضًا فِي كَنِيسَةِ ٱللَّاوُدِكِيِّينَ، وَٱلَّتِي مِنْ لَاوُدِكِيَّةَ تَقْرَأُونَهَا أَنْتُمْ أَيْضًا."},{"id":798102,"bibleId":11,"bookId":51,"chapter":4,"number":17,"text":"وَقُولُوا لِأَرْخِبُّسَ: «ٱنْظُرْ إِلَى ٱلْخِدْمَةِ ٱلَّتِي قَبِلْتَهَا فِي ٱلرَّبِّ لِكَيْ تُتَمِّمَهَا»."},{"id":798103,"bibleId":11,"bookId":51,"chapter":4,"number":18,"text":"اَلسَّلَامُ بِيَدِي أَنَا بُولُسَ. اُذْكُرُوا وُثُقِي. اَلنِّعْمَةُ مَعَكُمْ. آمِينَ. -كُتِبَتْ إِلَى أَهْلِ كُولُسِّي مِنْ رُومِيَةِ بِيَدِ تِيخِيكُسَ وَ أُنِسِمُسَ-"}]}],"html":null}]},{"id":4,"title":"الكاثوليكون","introduction":null,"readings":[{"id":4,"title":null,"introduction":"الكاثوليكون من رسالة يعقوب الرسول  . بركاته تكون معنى أمين","conclusion":"لا تحبوا العالم ولا الأشياء التي في العالم؛ لأن العالم يمضي وشهوته. أما الذي يصنع إرادة الله فيثبت إلى الأبد. آمين.","passages":[{"bookId":59,"bookTranslation":"يعقوب","chapter":5,"ref":"5:9-20","verses":[{"id":798906,"bibleId":11,"bookId":59,"chapter":5,"number":9,"text":"لَا يَئِنَّ بَعْضُكُمْ عَلَى بَعْضٍ أَيُّهَا ٱلْإِخْوَةُ لِئَلَّا تُدَانُوا. هُوَذَا ٱلدَّيَّانُ وَاقِفٌ قُدَّامَ ٱلْبَابِ."},{"id":798907,"bibleId":11,"bookId":59,"chapter":5,"number":10,"text":"خُذُوا يَا إِخْوَتِي مِثَالًا لِٱحْتِمَالِ ٱلْمَشَقَّاتِ وَٱلْأَنَاةِ: ٱلْأَنْبِيَاءَ ٱلَّذِينَ تَكَلَّمُوا بِٱسْمِ ٱلرَّبِّ."},{"id":798908,"bibleId":11,"bookId":59,"chapter":5,"number":11,"text":"هَا نَحْنُ نُطَوِّبُ ٱلصَّابِرِينَ. قَدْ سَمِعْتُمْ بِصَبْرِ أَيُّوبَ وَرَأَيْتُمْ عَاقِبَةَ ٱلرَّبِّ. لِأَنَّ ٱلرَّبَّ كَثِيرُ ٱلرَّحْمَةِ وَرَؤُوفٌ."},{"id":798909,"bibleId":11,"bookId":59,"chapter":5,"number":12,"text":"وَلَكِنْ قَبْلَ كُلِّ شَيْءٍ يَا إِخْوَتِي، لَا تَحْلِفُوا، لَا بِٱلسَّمَاءِ، وَلَا بِٱلْأَرْضِ، وَلَا بِقَسَمٍ آخَرَ. بَلْ لِتَكُنْ نَعَمْكُمْ نَعَمْ، وَلَاكُمْ لَا، لِئَلَّا تَقَعُوا تَحْتَ دَيْنُونَةٍ."},{"id":798910,"bibleId":11,"bookId":59,"chapter":5,"number":13,"text":"أَعَلَى أَحَدٍ بَيْنَكُمْ مَشَقَّاتٌ؟ فَلْيُصَلِّ. أَمَسْرُورٌ أَحَدٌ؟ فَلْيُرَتِّلْ."},{"id":798911,"bibleId":11,"bookId":59,"chapter":5,"number":14,"text":"أَمَرِيضٌ أَحَدٌ بَيْنَكُمْ؟ فَلْيَدْعُ شُيُوخَ ٱلْكَنِيسَةِ فَيُصَلُّوا عَلَيْهِ وَيَدْهُنُوهُ بِزَيْتٍ بِٱسْمِ ٱلرَّبِّ،"},{"id":798912,"bibleId":11,"bookId":59,"chapter":5,"number":15,"text":"وَصَلَاةُ ٱلْإِيمَانِ تَشْفِي ٱلْمَرِيضَ، وَٱلرَّبُّ يُقِيمُهُ، وَإِنْ كَانَ قَدْ فَعَلَ خَطِيَّةً تُغْفَرُ لَهُ."},{"id":798913,"bibleId":11,"bookId":59,"chapter":5,"number":16,"text":"اِعْتَرِفُوا بَعْضُكُمْ لِبَعْضٍ بِٱلزَلَّاتِ، وَصَلُّوا بَعْضُكُمْ لِأَجْلِ بَعْضٍ، لِكَيْ تُشْفَوْا. طَلِبَةُ ٱلْبَارِّ تَقْتَدِرُ كَثِيرًا فِي فِعْلِهَا."},{"id":798914,"bibleId":11,"bookId":59,"chapter":5,"number":17,"text":"كَانَ إِيلِيَّا إِنْسَانًا تَحْتَ ٱلْآلَامِ مِثْلَنَا، وَصَلَّى صَلَاةً أَنْ لَا تُمْطِرَ، فَلَمْ تُمْطِرْ عَلَى ٱلْأَرْضِ ثَلَاثَ سِنِينَ وَسِتَّةَ أَشْهُرٍ."},{"id":798915,"bibleId":11,"bookId":59,"chapter":5,"number":18,"text":"ثُمَّ صَلَّى أَيْضًا، فَأَعْطَتِ ٱلسَّمَاءُ مَطَرًا، وَأَخْرَجَتِ ٱلْأَرْضُ ثَمَرَهَا."},{"id":798916,"bibleId":11,"bookId":59,"chapter":5,"number":19,"text":"أَيُّهَا ٱلْإِخْوَةُ، إِنْ ضَلَّ أَحَدٌ بَيْنَكُمْ عَنِ ٱلْحَقِّ فَرَدَّهُ أَحَدٌ،"},{"id":798917,"bibleId":11,"bookId":59,"chapter":5,"number":20,"text":"فَلْيَعْلَمْ أَنَّ مَنْ رَدَّ خَاطِئًا عَنْ ضَلَالِ طَرِيقِهِ، يُخَلِّصُ نَفْسًا مِنَ ٱلْمَوْتِ، وَيَسْتُرُ كَثْرَةً مِنَ ٱلْخَطَايَا."}]}],"html":null}]},{"id":5,"title":"الابركسيس","introduction":null,"readings":[{"id":5,"title":null,"introduction":"فصل من اعمال آبائنأ الرسل الأطهار المشمولين بنعمة الروح القدس، بركتهم تكون معنا. آمين.","conclusion":"لم تزل كلمة الرب تنمو وتعتز وتثبت في كنيسة الله المقدسة. آمين.","passages":[{"bookId":44,"bookTranslation":"اعمال","chapter":18,"ref":"18:1-11","verses":[{"id":796101,"bibleId":11,"bookId":44,"chapter":18,"number":1,"text":"وَبَعْدَ هَذَا مَضَى بُولُسُ مِنْ أَثِينَا وَجَاءَ إِلَى كُورِنْثُوسَ،"},{"id":796102,"bibleId":11,"bookId":44,"chapter":18,"number":2,"text":"فَوَجَدَ يَهُودِيًّا ٱسْمُهُ أَكِيلَا، بُنْطِيَّ ٱلْجِنْسِ، كَانَ قَدْ جَاءَ حَدِيثًا مِنْ إِيطَالِيَةَ، وَبِرِيسْكِلَّا ٱمْرَأَتَهُ، لِأَنَّ كُلُودِيُوسَ كَانَ قَدْ أَمَرَ أَنْ يَمْضِيَ جَمِيعُ ٱلْيَهُودِ مِنْ رُومِيَةَ، فَجَاءَ إِلَيْهِمَا."},{"id":796103,"bibleId":11,"bookId":44,"chapter":18,"number":3,"text":"وَلِكَوْنِهِ مِنْ صِنَاعَتِهِمَا أَقَامَ عِنْدَهُمَا وَكَانَ يَعْمَلُ، لِأَنَّهُمَا كَانَا فِي صِنَاعَتِهِمَا خِيَامِيَّيْنِ."},{"id":796104,"bibleId":11,"bookId":44,"chapter":18,"number":4,"text":"وَكَانَ يُحَاجُّ فِي ٱلْمَجْمَعِ كُلَّ سَبْتٍ وَيُقْنِعُ يَهُودًا وَيُونَانِيِّينَ."},{"id":796105,"bibleId":11,"bookId":44,"chapter":18,"number":5,"text":"وَلَمَّا ٱنْحَدَرَ سِيلَا وَتِيمُوثَاوُسُ مِنْ مَكِدُونِيَّةَ، كَانَ بُولُسُ مُنْحَصِرًا بِٱلرُّوحِ وَهُوَ يَشْهَدُ لِلْيَهُودِ بِٱلْمَسِيحِ يَسُوعَ."},{"id":796106,"bibleId":11,"bookId":44,"chapter":18,"number":6,"text":"وَإِذْ كَانُوا يُقَاوِمُونَ وَيُجَدِّفُونَ نَفَضَ ثِيَابَهُ وَقَالَ لَهُمْ: «دَمُكُمْ عَلَى رُؤُوسِكُمْ! أَنَا بَرِيءٌ. مِنَ ٱلْآنَ أَذْهَبُ إِلَى ٱلْأُمَمِ»."},{"id":796107,"bibleId":11,"bookId":44,"chapter":18,"number":7,"text":"فَٱنْتَقَلَ مِنْ هُنَاكَ وَجَاءَ إِلَى بَيْتِ رَجُلٍ ٱسْمُهُ يُوسْتُسُ، كَانَ مُتَعَبِّدًا لِلهِ، وَكَانَ بَيْتُهُ مُلَاصِقًا لِلْمَجْمَعِ."},{"id":796108,"bibleId":11,"bookId":44,"chapter":18,"number":8,"text":"وَكِرِيسْبُسُ رَئِيسُ ٱلْمَجْمَعِ آمَنَ بِٱلرَّبِّ مَعَ جَمِيعِ بَيْتِهِ، وَكَثِيرُونَ مِنَ ٱلْكُورِنْثِيِّينَ إِذْ سَمِعُوا آمَنُوا وَٱعْتَمَدُوا."},{"id":796109,"bibleId":11,"bookId":44,"chapter":18,"number":9,"text":"فَقَالَ ٱلرَّبُّ لِبُولُسَ بِرُؤْيَا فيِ ٱللَّيْلِ: «لَا تَخَفْ، بَلْ تَكَلَّمْ وَلَا تَسْكُتْ،"},{"id":796110,"bibleId":11,"bookId":44,"chapter":18,"number":10,"text":"لِأَنِّي أَنَا مَعَكَ، وَلَا يَقَعُ بِكَ أَحَدٌ لِيُؤْذِيَكَ، لِأَنَّ لِي شَعْبًا كَثِيرًا فِي هَذِهِ ٱلْمَدِينَةِ»."},{"id":796111,"bibleId":11,"bookId":44,"chapter":18,"number":11,"text":"فَأَقَامَ سَنَةً وَسِتَّةَ أَشْهُرٍ يُعَلِّمُ بَيْنَهُمْ بِكَلِمَةِ ٱللهِ."}]}],"html":null}]},{"id":10,"title":"السنكسار","introduction":"اليوم 28 من الشهر المبارك Baounah, أحسن الله استقباله، وأعاده علينا وعليكم، ونحن في هدوء واطمئنان، مغفوري الخطايا والآثام، من قِبَل مراحم الرب، يا آبائي وأخوتي.\r\nآمين.","readings":[{"id":6,"title":"نياحة البابا ثاؤذورس \"33 \" ","introduction":null,"conclusion":null,"passages":null,"html":"<p>في مثل هذا اليوم من سنة 283 ش ( 22 يونيو سنة 567 م ) تنيح \nالقديس ثاؤدسيوس البطريرك الثالث والثلاثين من باباوات الكرازة المرقسية . وذلك أنه \nبعد نياحة تيموثاوس أجتمع الأساقفة والشعب الأرثوذكسي ورسموا هذا الأب بطريركا وكان \nعالما حافظا لكتب الكنيسة وبعد أيام أثار عليه عدو الخير قوما أشرارا من أهل \nالمدينة وأخذوا فاكيوس رئيس شمامسة كنيسة الإسكندرية ورسموه بطريركا بمعاونة \nيوليانوس . الذي كان البابا تيموثاوس قد حرمه لموافقته لمجمع خلقيدونية .ولما رسم \nفاكيوس نفوا البابا ثاؤدسيوس إلى جرسيمانوس وكان القديس ساويرس الأنطاكي يقيم في \nسخا من بلاد مصر وكان يعزيه ويصبره ذاكرا له ماخري للرسل وليوحنا ذهبي الفم . وبعد \nستة أشهر من نفيه ذهب إلى مليج وأقام بها سنتين وبعد ذلك تقدم أهل الإسكندرية إلى \nالوالي وطلبوا منه أن يأمر بإعادة راعيهم الشرعي وطرد فاكيوس الدخيل ووصل الخبر إلى \nالملك يوستينيانوس والملكة المحبة للإله ثاؤذورا . فأرسلت تسأل عن صحة رسامة البابا \nثاؤدسيوس حتى إذا كانت طبق القانون يتسلم كرسيه فعقدوا مجمعا من الشعب ومائة وعشرين \nكاهنا وأجمعوا علي أن ثاؤدسيوس رسم باتفاق الأساقفة والشعب وفقا للقانون . وكان \nفاكيوس حاضرا في المجمع فوقف معترفا بأنه هو المعتدي وطلب مسامحته علي أن يبقي رئيس \nشمامسة كما كان قبلا وأرسلوا للملكة بذلك غير أنه لما كان الملك موافقا علي معتقد \nغير الصحيح فكتب إلى نائبه في الإسكندرية يقول : \" إذا اتفق معنا البطريرك ثاؤدسيوس \nفي الإيمان فتضاف إليه مع البطريركية الولاية علي الإسكندرية وإذ لم يوافق يخرج من \nالمدينة \" فلما سمع البطريرك هذا القول قال : \" هكذا الشيطان قال للسيد المسيح بعد \nما أراه جميع مماليك العالم ومجدها أعطيك هذه جميعها أن خررت وسجدت لي \" (مت 4 : 8 \nو 9) ثم خرج من المدينة ومضي إلى الصعيد وأقام هناك يثبت ثم استدعاه الملك إلى \nالقسطنطينية فذهب إليها مع بعض الكهنة العلماء فتلقاه الملك بإكرام عظيم وأجلسه في \nمكان ممتاز واخذ بتملقه ويخاطبه بلطف لكي يوافق علي معتقد مجمع خلقيدونية وإذ لم \nيوافقه نفاه إلى صعيد مصر وأقام عوضا عنه شخصا يسمي بولس فلما وصل هذا إلى \nالإسكندرية لم يقبله أهلها ولبث سنة لم يتقرب إليه إلا نفر قليل . ولما وصل هذا \nالآمر إلى الملك آمر بإغلاق الكنائس حتى يخضعوا للبطريرك الذي عينه الملك فبني \nالمؤمنون كنيسة علي اسم القديس مرقس خارج المدينة وأخري علي اسم القديسين قزمان \nودميان وكانوا يتقربون فيهما ويعمدون أولادهم .</p><p>ولما سمع الملك بذلك عاد فأمر بفتح الكنائس فلما سمع البابا \nثاؤدسيوس بهذا الآمر خشي أن يكون الملك قد قصد بذلك أن يستميلهم فكتب لهم رسالة \nيثبتهم علي الإيمان المستقيم ويحذرهم من خداع ذلك المخالف . وأقام في المنفي ثمان \nوعشرين سنة في صعيد مصر وأربع سنين في مدينة الإسكندرية وأمضي في البطريركية واحدا \nوثلاثين سنة وأربعة أشهر وخمسة عشر يوما وقد وضع هذا البابا ميامر وتعاليم كثيرة \nصلاته تكون معنا . آمين</p>"},{"id":6,"title":"تذكار تكريس كنيسة الأنبا صرابامون أسقف نيقيوس ","introduction":null,"conclusion":null,"passages":null,"html":"<p>في هذا اليوم نعيد بتذكار تكريس كنيسة الشهيد الأنبا صرابامون \nأسقف نقيوس.</p><p>صلاته تكون معنا ولربنا المجد دائما . آمين</p>"}]},{"id":1,"title":"المزمور والإنجيل","introduction":"قفوا بخوف أمام الله، وانصتوا لسماع الإنجيل المقدس. فصل شريف من بشارة معلمنا لوقا الإنجيلي. بركته تكون مع جميعنا، آمين.","readings":[{"id":1,"title":null,"introduction":"من مزامير أبينا داود النبي والملك ، بركاته يكون معنا أمين","conclusion":"هللويا!","passages":[{"bookId":19,"bookTranslation":"مزامير","chapter":69,"ref":"69:32,33,30","verses":[{"id":783510,"bibleId":11,"bookId":19,"chapter":69,"number":32,"text":"يَرَى ذَلِكَ ٱلْوُدَعَاءُ فَيَفْرَحُونَ، وَتَحْيَا قُلُوبُكُمْ يَا طَالِبِي ٱللهِ."},{"id":783511,"bibleId":11,"bookId":19,"chapter":69,"number":33,"text":"لِأَنَّ ٱلرَّبَّ سَامِعٌ لِلْمَسَاكِينِ وَلَا يَحْتَقِرُ أَسْرَاهُ."},{"id":783508,"bibleId":11,"bookId":19,"chapter":69,"number":30,"text":"أُسَبِّحُ ٱسْمَ ٱللهِ بِتَسْبِيحٍ، وَأُعَظِّمُهُ بِحَمْدٍ."}]}],"html":null},{"id":2,"title":null,"introduction":"مبارك الآتي باسم الرب إله القوات ، ربنا وإلهنا ومخلصنا وملكنا كلنا، يسوع المسيح ابن الله الحي، الذي له المجد للأبد آمين.","conclusion":"ولله المجد لله الى الابد آمين.","passages":[{"bookId":42,"bookTranslation":"لوقا","chapter":6,"ref":"6:27-38","verses":[{"id":793716,"bibleId":11,"bookId":42,"chapter":6,"number":27,"text":"«لَكِنِّي أَقُولُ لَكُمْ أَيُّهَا ٱلسَّامِعُونَ: أَحِبُّوا أَعْدَاءَكُمْ، أَحْسِنُوا إِلَى مُبْغِضِيكُمْ،"},{"id":793717,"bibleId":11,"bookId":42,"chapter":6,"number":28,"text":"بَارِكُوا لَاعِنِيكُمْ، وَصَلُّوا لِأَجْلِ ٱلَّذِينَ يُسِيئُونَ إِلَيْكُمْ."},{"id":793718,"bibleId":11,"bookId":42,"chapter":6,"number":29,"text":"مَنْ ضَرَبَكَ عَلَى خَدِّكَ فَٱعْرِضْ لَهُ ٱلْآخَرَ أَيْضًا، وَمَنْ أَخَذَ رِدَاءَكَ فَلَا تَمْنَعْهُ ثَوْبَكَ أَيْضًا."},{"id":793719,"bibleId":11,"bookId":42,"chapter":6,"number":30,"text":"وَكُلُّ مَنْ سَأَلَكَ فَأَعْطِهِ، وَمَنْ أَخَذَ ٱلَّذِي لَكَ فَلَا تُطَالِبْهُ."},{"id":793720,"bibleId":11,"bookId":42,"chapter":6,"number":31,"text":"وَكَمَا تُرِيدُونَ أَنْ يَفْعَلَ ٱلنَّاسُ بِكُمُ ٱفْعَلُوا أَنْتُمْ أَيْضًا بِهِمْ هَكَذَا."},{"id":793721,"bibleId":11,"bookId":42,"chapter":6,"number":32,"text":"وَإِنْ أَحْبَبْتُمُ ٱلَّذِينَ يُحِبُّونَكُمْ، فَأَيُّ فَضْلٍ لَكُمْ؟ فَإِنَّ ٱلْخُطَاةَ أَيْضًا يُحِبُّونَ ٱلَّذِينَ يُحِبُّونَهُمْ."},{"id":793722,"bibleId":11,"bookId":42,"chapter":6,"number":33,"text":"وَإِذَا أَحْسَنْتُمْ إِلَى ٱلَّذِينَ يُحْسِنُونَ إِلَيْكُمْ، فَأَيُّ فَضْلٍ لَكُمْ؟ فَإِنَّ ٱلْخُطَاةَ أَيْضًا يَفْعَلُونَ هَكَذَا."},{"id":793723,"bibleId":11,"bookId":42,"chapter":6,"number":34,"text":"وَإِنْ أَقْرَضْتُمُ ٱلَّذِينَ تَرْجُونَ أَنْ تَسْتَرِدُّوا مِنْهُمْ، فَأَيُّ فَضْلٍ لَكُمْ؟ فَإِنَّ ٱلْخُطَاةَ أَيْضًا يُقْرِضُونَ ٱلْخُطَاةَ لِكَيْ يَسْتَرِدُّوا مِنْهُمُ ٱلْمِثْلَ."},{"id":793724,"bibleId":11,"bookId":42,"chapter":6,"number":35,"text":"بَلْ أَحِبُّوا أَعْدَاءَكُمْ، وَأَحْسِنُوا وَأَقْرِضُوا وَأَنْتُمْ لَا تَرْجُونَ شَيْئًا، فَيَكُونَ أَجْرُكُمْ عَظِيمًا وَتَكُونُوا بَنِي ٱلْعَلِيِّ، فَإِنَّهُ مُنْعِمٌ عَلَى غَيْرِ ٱلشَّاكِرِينَ وَٱلْأَشْرَارِ."},{"id":793725,"bibleId":11,"bookId":42,"chapter":6,"number":36,"text":"فَكُونُوا رُحَمَاءَ كَمَا أَنَّ أَبَاكُمْ أَيْضًا رَحِيمٌ."},{"id":793726,"bibleId":11,"bookId":42,"chapter":6,"number":37,"text":"«وَلَا تَدِينُوا فَلَا تُدَانُوا. لَا تَقْضُوا عَلَى أَحَدٍ فَلَا يُقْضَى عَلَيْكُمْ. اِغْفِرُوا يُغْفَرْ لَكُمْ."},{"id":793727,"bibleId":11,"bookId":42,"chapter":6,"number":38,"text":"أَعْطُوا تُعْطَوْا، كَيْلًا جَيِّدًا مُلَبَّدًا مَهْزُوزًا فَائِضًا يُعْطُونَ فِي أَحْضَانِكُمْ. لِأَنَّهُ بِنَفْسِ ٱلْكَيْلِ ٱلَّذِي بِهِ تَكِيلُونَ يُكَالُ لَكُمْ»."}]}],"html":null}]}]}],"copticDate":"28/10/1742"}